joolyterdemo/__init__.py
joolyterdemo/functions.py
joolyterdemo/interpreter.py
joolyterdemo/maneuver.py
joolyterdemo/mission_solution.py
joolyterdemo-0.3.6.dist-info/METADATA
joolyterdemo-0.3.6.dist-info/WHEEL
joolyterdemo-0.3.6.dist-info/top_level.txt
joolyterdemo-0.3.6.dist-info/RECORD
