Metadata-Version: 2.1
Name: joolyterdemo
Version: 0.3.6
Summary: Python package that goes with Joolyter gamification approach.
Home-page: UNKNOWN
Author: Paul J. Schmiedtke
License: None
Platform: UNKNOWN
Requires-Dist: protobuf (==3.19.4)
Requires-Dist: setuptools (==57.5.0)
Requires-Dist: krpc
Requires-Dist: p2j
Requires-Dist: jupyterlab
